pydc_auth/__init__.py
pydc_auth/datacloud/__init__.py
pydc_auth/datacloud/dc_token_exchange.py
pydc_auth/sfauth/__init__.py
pydc_auth/sfauth/jwt_token_creator.py
pydc_auth/sfauth/sf_token_exchange.py
pydc_auth-0.1.3.dist-info/licenses/LICENSE
pydc_auth-0.1.3.dist-info/METADATA
pydc_auth-0.1.3.dist-info/WHEEL
pydc_auth-0.1.3.dist-info/top_level.txt
pydc_auth-0.1.3.dist-info/RECORD
