Metadata-Version: 2.4
Name: pydc-auth
Version: 0.1.3
Summary: JWT Bearer Auth client for generating Salesforce Data Cloud Bearer Access Token
Author: Makarand Bhonsle
License-Expression: MIT
Project-URL: Homepage, https://github.com/mbhonsle/pydc-auth
Project-URL: Issues, https://github.com/mbhonsle/pydc-auth/issues
Classifier: Development Status :: 5 - Production/Stable
Classifier: Intended Audience :: Developers
Classifier: Operating System :: OS Independent
Classifier: Programming Language :: Python
Classifier: Programming Language :: Python :: 3
Classifier: Programming Language :: Python :: 3 :: Only
Classifier: Programming Language :: Python :: 3.12
Classifier: Topic :: Security
Classifier: Topic :: Internet :: WWW/HTTP
Classifier: Topic :: Software Development :: Libraries :: Python Modules
Requires-Python: >=3.12
License-File: LICENSE
Requires-Dist: httpx>=0.28.1
Requires-Dist: python-dotenv>=1.0.0
Requires-Dist: PyJWT>=2.8.0
Requires-Dist: cryptography>=41.0.0
Requires-Dist: tenacity>=9.0.0
Requires-Dist: pydantic>=1.10
Dynamic: license-file
